manychat/__init__.py
manychat/api.py
manychat/fb/__init__.py
manychat/fb/page.py
manychat/fb/sending.py
manychat/fb/subscriber.py
manychat_python-0.1.4.dist-info/LICENSE
manychat_python-0.1.4.dist-info/METADATA
manychat_python-0.1.4.dist-info/WHEEL
manychat_python-0.1.4.dist-info/RECORD
